{
	"name": "Eldritch Vision",
	"type": "history_event",
	"_id": "1uls8S31H3EvMlxx",
	"img": "icons/svg/item-bag.svg",
	"system": {
		"attributes": {
			"close": 0,
			"far": 1,
			"mental": 0,
			"evasion": 0,
			"willpower": 0,
			"speed": 0,
			"power": 0,
			"weight": 0,
			"baseAP": 0,
			"sensors": 0,
			"ballast": 0
		},
		"type": "touch",
		"description": "It is as if a veil has been lifted from your eyes. You see more clearly now, how many more times until you see too much?",
		"mechanics": "Gain +1 to your FAR stat."
	},
	"effects": [],
	"folder": null,
	"sort": 0,
	"ownership": {
		"default": 0,
		"Z70QWDl1bY0su5ht": 3
	},
	"flags": {},
	"_stats": {
		"systemId": "fathomlessgears",
		"systemVersion": "#{VERSION}#",
		"coreVersion": "11.315",
		"createdTime": 1734931992211,
		"modifiedTime": 1734931992211,
		"lastModifiedBy": "Z70QWDl1bY0su5ht"
	},
	"_key": "!items!1uls8S31H3EvMlxx"
}
